NES-2026/PD/rtl/mux41/mux41.v
module mux41 (
    input  wire d0,
    input  wire d1,
    input  wire d2,
    input  wire d3,
    input  wire [1:0] sel,
    output reg  y
);

always @(*) begin
    case (sel)
        2'b00: y = d0;
        2'b01: y = d1;
        2'b10: y = d2;
        2'b11: y = d3;
        default: y = 1'b0;
    endcase
end

endmodule

NES-2026/PD/rtl/mux41/mux41_tb.v
`timescale 1ns/1ps 
 
module tb_mux41; 
 
    reg d0; 
    reg d1; 
    reg d2; 
    reg d3; 
    reg [1:0] sel; 
    wire y; 
 
    // Instantiate DUT 
    mux41 dut ( 
        .d0(d0), 
        .d1(d1), 
        .d2(d2), 
        .d3(d3), 
        .sel(sel), 
        .y(y) 
    ); 
 
    initial begin 
        // Dump waveform 
        $dumpfile("mux41.vcd"); 
        $dumpvars(0, tb_mux41); 
 
        // Initialize signals 
        d0 = 0; 
        d1 = 1; 
        d2 = 0; 
        d3 = 1; 
        sel = 2'b00; 
 
        // Apply different select values 
        #10 sel = 2'b00;   // expect y = d0 
        #10 sel = 2'b01;   // expect y = d1 
        #10 sel = 2'b10;   // expect y = d2 
        #10 sel = 2'b11;   // expect y = d3 
 
        // Change inputs 
        #10 d0 = 1; d1 = 0; d2 = 1; d3 = 0; 
 
        #10 sel = 2'b00; 
        #10 sel = 2'b01; 
        #10 sel = 2'b10; 
        #10 sel = 2'b11; 
 
        #20 $finish; 
    end 
 
endmodule

NES-2026/PD/rtl/mux41/mux41.vcd
$date
	Thu Feb 12 10:29:51 2026
$end
$version
	Icarus Verilog
$end
$timescale
	1ps
$end
$scope module tb_mux41 $end
$var wire 1 ! y $end
$var reg 1 " d0 $end
$var reg 1 # d1 $end
$var reg 1 $ d2 $end
$var reg 1 % d3 $end
$var reg 2 & sel [1:0] $end
$scope module dut $end
$var wire 1 " d0 $end
$var wire 1 # d1 $end
$var wire 1 $ d2 $end
$var wire 1 % d3 $end
$var wire 2 ' sel [1:0] $end
$var reg 1 ! y $end
$upscope $end
$upscope $end
$enddefinitions $end
$comment Show the parameter values. $end
$dumpall
$end
#0
$dumpvars
b0 '
b0 &
1%
0$
1#
0"
0!
$end
#20000
1!
b1 &
b1 '
#30000
0!
b10 &
b10 '
#40000
1!
b11 &
b11 '
#50000
0!
0%
1$
0#
1"
#60000
1!
b0 &
b0 '
#70000
0!
b1 &
b1 '
#80000
1!
b10 &
b10 '
#90000
0!
b11 &
b11 '
